ampy/__init__.py
ampy/cli.py
ampy/files.py
ampy/pyboard.py
adafruit_ampy-1.1.0.dist-info/LICENSE
adafruit_ampy-1.1.0.dist-info/METADATA
adafruit_ampy-1.1.0.dist-info/WHEEL
adafruit_ampy-1.1.0.dist-info/entry_points.txt
adafruit_ampy-1.1.0.dist-info/top_level.txt
adafruit_ampy-1.1.0.dist-info/RECORD
